scraping_rtn/RtnSingleTeamYear.py
scraping_rtn/__init__.py
scraping_rtn/src.py
scraping_rtn-0.0.8.2.dist-info/METADATA
scraping_rtn-0.0.8.2.dist-info/WHEEL
scraping_rtn-0.0.8.2.dist-info/top_level.txt
scraping_rtn-0.0.8.2.dist-info/RECORD
