Metadata-Version: 2.4
Name: scraping_rtn
Version: 0.0.8.2
Summary: package to scrape gymnastics data from Road To Nationals
Author-email: Claire Harmon <ceharmon220@gmail.com>
License: MIT
Project-URL: Homepage, https://github.com/ceharmon/scraping_rtn
Classifier: Programming Language :: Python :: 3
Classifier: License :: OSI Approved :: MIT License
Classifier: Operating System :: OS Independent
Requires-Python: >=3.9
Requires-Dist: pandas>=1.5.3
Requires-Dist: numpy>=1.23.5
Requires-Dist: requests>=2.28.1
